mcp_base64/__init__.py
mcp_base64/server.py
mcp_base64-0.1.4.dist-info/METADATA
mcp_base64-0.1.4.dist-info/WHEEL
mcp_base64-0.1.4.dist-info/entry_points.txt
mcp_base64-0.1.4.dist-info/licenses/LICENSE
mcp_base64-0.1.4.dist-info/RECORD
