Metadata-Version: 2.4
Name: mcp-base64
Version: 0.1.4
Summary: MCP server for Base64 file conversion (stdio transport)
Author: Stefan Kuhn
License: MIT
License-File: LICENSE
Keywords: base64,cli,fastmcp,mcp
Classifier: Intended Audience :: Developers
Classifier: License :: OSI Approved :: MIT License
Classifier: Programming Language :: Python :: 3
Classifier: Programming Language :: Python :: 3.10
Classifier: Programming Language :: Python :: 3.11
Classifier: Programming Language :: Python :: 3.12
Requires-Python: >=3.10
Requires-Dist: fastmcp>=0.2.0
Requires-Dist: pydantic>=2.0.0
Provides-Extra: dev
Requires-Dist: hatch; extra == 'dev'
Requires-Dist: pytest-asyncio>=0.21.0; extra == 'dev'
Requires-Dist: pytest>=7.0.0; extra == 'dev'
Requires-Dist: ruff>=0.1.0; extra == 'dev'
